dimed/__init__.py
dimed/cli.py
dimed/template/cookiecutter.json
dimed/template/{{cookiecutter.dimedfolder}}/__init__.py
dimed/template/{{cookiecutter.dimedfolder}}/__main__.py
dimed-0.2.dist-info/METADATA
dimed-0.2.dist-info/WHEEL
dimed-0.2.dist-info/entry_points.txt
dimed-0.2.dist-info/top_level.txt
dimed-0.2.dist-info/RECORD
