Metadata-Version: 2.1
Name: dimed
Version: 0.2
Summary: Dimed for CLI and packaging
Author-email: Dmitry Sorokin <dmd40in@gmail.com>
Requires-Dist: click
Requires-Dist: cookiecutter
Requires-Dist: dimed-2
